5 - Uni Logic Gates using Switch Modeling/nor_gate.v
`timescale 1ns/1ps

module nor_gate(
    input vin1, vin2,
    output vout    
    );

    supply0 gnd;
    supply1 vdd;
    wire temp;
    pmos(temp, vdd, vin1);
    pmos(vout, temp, vin2);
    nmos(vout, gnd, vin1);
    nmos(vout, gnd, vin2);
endmodule

5 - Uni Logic Gates using Switch Modeling/nor_tb.v
`timescale 1ns/1ps
`include "nor_gate.v"

module nor_tb;
    reg vin1, vin2;
    wire vout;

    nor_gate dut( vin1, vin2, vout);
    initial $dumpfile("nor_tb.vcd");
    initial $dumpvars(0, nor_tb);

    initial vin1= 1'b0;
    initial vin2= 1'b0;
    initial repeat(15) #50 vin1 = ~vin1; 
    initial repeat(15) #100 vin2 = ~vin2; 
    initial #600 $finish;
endmodule

5 - Uni Logic Gates using Switch Modeling/nor_tb.vcd
$date
	Fri Sep 19 20:04:59 2025
$end
$version
	Icarus Verilog
$end
$timescale
	1ps
$end
$scope module nor_tb $end
$var wire 1 ! vout $end
$var reg 1 " vin1 $end
$var reg 1 # vin2 $end
$scope module dut $end
$var wire 1 $ gnd $end
$var wire 1 % temp $end
$var wire 1 & vdd $end
$var wire 1 " vin1 $end
$var wire 1 # vin2 $end
$var wire 1 ! vout $end
$upscope $end
$upscope $end
$enddefinitions $end
$comment Show the parameter values. $end
$dumpall
$end
#0
$dumpvars
1&
1%
0$
0#
0"
1!
$end
#50000
z%
0!
1"
#100000
1%
0"
1#
#150000
z%
1"
#200000
1%
1!
0"
0#
#250000
z%
0!
1"
#300000
1%
0"
1#
#350000
z%
1"
#400000
1%
1!
0"
0#
#450000
z%
0!
1"
#500000
1%
0"
1#
#550000
z%
1"
#600000
1%
1!
0"
0#
