6 - Even Parity generator and checker/even_parity_checker.v
`timescale 1ns/1ps

module even_parity_checker (
    input wire [3:0] data_in,
    input wire parity,
    output wire error
    );

    assign error = ^({parity, data_in});

endmodule

6 - Even Parity generator and checker/epc_tb.v
`timescale 1ns/1ps
`include "even_parity_checker.v"

module epc_tb;
    reg [3:0] data_in;
    reg parity;
    reg clk;
    wire error;

    even_parity_checker dut (data_in, parity, error);

    always #5 clk = ~clk;

    initial begin

        $dumpfile("epc_tb.vcd");
        $dumpvars(0, epc_tb);
        
        clk = 0;
        data_in = 4'b0000;
        parity = 0;
        #10;

        data_in = 4'b1011;
        parity = 1;
        #10;

        data_in = 4'b1100;
        parity = 0;
        #10;

        data_in = 4'b1111;
        parity = 0;
        #10;

        // now to check the erors 

        data_in = 4'b0000;
        parity = 1;
        #10;

        data_in = 4'b1011;
        parity = 0;
        #10;

        data_in = 4'b1100;
        parity = 1;
        #10;

        data_in = 4'b1111;
        parity = 1;
        #10; 

        $finish;
    end

        always @(posedge clk) begin
            $display("Data = %b, Parity = %b, Error = %b", data_in, parity, error);
        end
endmodule

6 - Even Parity generator and checker/epc_tb.vcd
$date
	Sun Sep 21 21:25:02 2025
$end
$version
	Icarus Verilog
$end
$timescale
	1ps
$end
$scope module epc_tb $end
$var wire 1 ! error $end
$var reg 1 " clk $end
$var reg 4 # data_in [3:0] $end
$var reg 1 $ parity $end
$scope module dut $end
$var wire 4 % data_in [3:0] $end
$var wire 1 $ parity $end
$var wire 1 ! error $end
$upscope $end
$upscope $end
$enddefinitions $end
$comment Show the parameter values. $end
$dumpall
$end
#0
$dumpvars
b0 %
0$
b0 #
0"
0!
$end
#5000
1"
#10000
0"
1$
0!
b1011 #
b1011 %
#15000
1"
#20000
0"
0$
0!
b1100 #
b1100 %
#25000
1"
#30000
0"
b1111 #
b1111 %
#35000
1"
#40000
0"
1!
1$
b0 #
b0 %
#45000
1"
#50000
0"
0$
1!
b1011 #
b1011 %
#55000
1"
#60000
0"
1$
1!
b1100 #
b1100 %
#65000
1"
#70000
0"
b1111 #
b1111 %
